metaflow_extensions/obcheckpoint/plugins/__init__.py
metaflow_extensions/obcheckpoint/plugins/datastores/s3_compat.py
metaflow_extensions/obcheckpoint/plugins/machine_learning_utilities/__init__.py
metaflow_extensions/obcheckpoint/plugins/machine_learning_utilities/datastructures.py
metaflow_extensions/obcheckpoint/plugins/machine_learning_utilities/exceptions.py
metaflow_extensions/obcheckpoint/plugins/machine_learning_utilities/card_utils/__init__.py
metaflow_extensions/obcheckpoint/plugins/machine_learning_utilities/card_utils/async_cards.py
metaflow_extensions/obcheckpoint/plugins/machine_learning_utilities/card_utils/deco_injection_mixin.py
metaflow_extensions/obcheckpoint/plugins/machine_learning_utilities/card_utils/extra_components.py
metaflow_extensions/obcheckpoint/plugins/machine_learning_utilities/checkpoints/__init__.py
metaflow_extensions/obcheckpoint/plugins/machine_learning_utilities/checkpoints/checkpoint_storage.py
metaflow_extensions/obcheckpoint/plugins/machine_learning_utilities/checkpoints/constants.py
metaflow_extensions/obcheckpoint/plugins/machine_learning_utilities/checkpoints/constructors.py
metaflow_extensions/obcheckpoint/plugins/machine_learning_utilities/checkpoints/core.py
metaflow_extensions/obcheckpoint/plugins/machine_learning_utilities/checkpoints/decorator.py
metaflow_extensions/obcheckpoint/plugins/machine_learning_utilities/checkpoints/exceptions.py
metaflow_extensions/obcheckpoint/plugins/machine_learning_utilities/checkpoints/final_api.py
metaflow_extensions/obcheckpoint/plugins/machine_learning_utilities/checkpoints/lineage.py
metaflow_extensions/obcheckpoint/plugins/machine_learning_utilities/checkpoints/cards/__init__.py
metaflow_extensions/obcheckpoint/plugins/machine_learning_utilities/checkpoints/cards/checkpoint_lister.py
metaflow_extensions/obcheckpoint/plugins/machine_learning_utilities/checkpoints/cards/diskspace_usage_card.py
metaflow_checkpoint-0.2.10.dist-info/METADATA
metaflow_checkpoint-0.2.10.dist-info/WHEEL
metaflow_checkpoint-0.2.10.dist-info/top_level.txt
metaflow_checkpoint-0.2.10.dist-info/RECORD
