Metadata-Version: 2.1
Name: metaflow_checkpoint
Version: 0.2.10
Summary: An EXPERIMENTAL checkpoint decorator for Metaflow
Author: Valay Dave
Author-email: help@outerbounds.com
